ovos_commonqa/__init__.py
ovos_commonqa/opm.py
ovos_commonqa/version.py
ovos_commonqa/locale/ca-es/Alerts.voc
ovos_commonqa/locale/ca-es/MiscBlacklist.voc
ovos_commonqa/locale/ca-es/Play.voc
ovos_commonqa/locale/ca-es/QuestionWord.voc
ovos_commonqa/locale/ca-es/Weather.voc
ovos_commonqa/locale/da-dk/Alerts.voc
ovos_commonqa/locale/da-dk/MiscBlacklist.voc
ovos_commonqa/locale/da-dk/Play.voc
ovos_commonqa/locale/da-dk/QuestionWord.voc
ovos_commonqa/locale/da-dk/Weather.voc
ovos_commonqa/locale/de-de/Alerts.voc
ovos_commonqa/locale/de-de/MiscBlacklist.voc
ovos_commonqa/locale/de-de/Play.voc
ovos_commonqa/locale/de-de/QuestionWord.voc
ovos_commonqa/locale/de-de/Weather.voc
ovos_commonqa/locale/en-us/Alerts.voc
ovos_commonqa/locale/en-us/MiscBlacklist.voc
ovos_commonqa/locale/en-us/Play.voc
ovos_commonqa/locale/en-us/QuestionWord.voc
ovos_commonqa/locale/en-us/Weather.voc
ovos_commonqa/locale/es-es/Alerts.voc
ovos_commonqa/locale/es-es/MiscBlacklist.voc
ovos_commonqa/locale/es-es/Play.voc
ovos_commonqa/locale/es-es/QuestionWord.voc
ovos_commonqa/locale/es-es/Weather.voc
ovos_commonqa/locale/eu/Alerts.voc
ovos_commonqa/locale/eu/Play.voc
ovos_commonqa/locale/eu/QuestionWord.voc
ovos_commonqa/locale/eu/Weather.voc
ovos_commonqa/locale/fr-fr/Play.voc
ovos_commonqa/locale/fr-fr/QuestionWord.voc
ovos_commonqa/locale/fr-fr/Weather.voc
ovos_commonqa/locale/gl-es/Alerts.voc
ovos_commonqa/locale/gl-es/Play.voc
ovos_commonqa/locale/gl-es/QuestionWord.voc
ovos_commonqa/locale/gl-es/Weather.voc
ovos_commonqa/locale/it-it/Play.voc
ovos_commonqa/locale/it-it/QuestionWord.voc
ovos_commonqa/locale/it-it/Weather.voc
ovos_commonqa/locale/nl-nl/Alerts.voc
ovos_commonqa/locale/nl-nl/MiscBlacklist.voc
ovos_commonqa/locale/nl-nl/Play.voc
ovos_commonqa/locale/nl-nl/QuestionWord.voc
ovos_commonqa/locale/nl-nl/Weather.voc
ovos_commonqa/locale/pt-br/Alerts.voc
ovos_commonqa/locale/pt-br/MiscBlacklist.voc
ovos_commonqa/locale/pt-br/Play.voc
ovos_commonqa/locale/pt-br/QuestionWord.voc
ovos_common_query_pipeline_plugin-1.1.9.dist-info/METADATA
ovos_common_query_pipeline_plugin-1.1.9.dist-info/WHEEL
ovos_common_query_pipeline_plugin-1.1.9.dist-info/entry_points.txt
ovos_common_query_pipeline_plugin-1.1.9.dist-info/top_level.txt
ovos_common_query_pipeline_plugin-1.1.9.dist-info/RECORD
