Metadata-Version: 2.4
Name: ovos_common_query_pipeline_plugin
Version: 1.1.9
Summary: question handling engine for OVOS
Home-page: https://github.com/OpenVoiceOS/ovos-common-query-pipeline-plugin
Author: JarbasAI
License: Apache License 2.0
Keywords: natural language processing
Classifier: Development Status :: 5 - Production/Stable
Classifier: Intended Audience :: Developers
Classifier: Topic :: Text Processing :: Linguistic
Classifier: License :: OSI Approved :: Apache Software License
Classifier: Programming Language :: Python :: 3.8
Classifier: Programming Language :: Python :: 3.9
Requires-Dist: ovos-workshop<8.0.0,>=0.1.7
Requires-Dist: ovos-plugin-manager<3.0.0,>=1.0.0
Requires-Dist: ovos-bus-client
Requires-Dist: ovos-config
Requires-Dist: ovos-utils<1.0.0,>=0.3.4
Provides-Extra: reranker
Requires-Dist: ovos-flashrank-reranker-plugin; extra == "reranker"
Dynamic: author
Dynamic: classifier
Dynamic: description-content-type
Dynamic: home-page
Dynamic: keywords
Dynamic: license
Dynamic: provides-extra
Dynamic: requires-dist
Dynamic: summary
